morphbpe/__init__.py
morphbpe-0.0.0.dist-info/METADATA
morphbpe-0.0.0.dist-info/WHEEL
morphbpe-0.0.0.dist-info/top_level.txt
morphbpe-0.0.0.dist-info/RECORD
